<?xml version="1.0" encoding="windows-1250" ?>
<string_table>
	<string id="st_save_wiz_scaner">
    <text>skener nainstalován</text>
</string>
<string id="st_save_uninvited_guests">
    <text>nepozvaní hosté</text>
</string>
<string id="st_save_bolotnaya_tvar_die">
    <text>bahenní bytost mrtvá</text>
</string>
<string id="st_save_katacombs">
    <text>nalezeny stopy skupiny</text>
</string>
<string id="st_save_path_two">
    <text>kapitola druhá - za všechno se platí</text>
</string>
<string id="st_save_in_hot_pursuit">
    <text>Podle stop - splněno</text>
</string>
<string id="st_save_dl_storyline_task_dolg">
    <text>navázat spojení s Dolem</text>
</string>
<string id="st_save_dl_sos_signal">
    <text>mozgovládce mrtvý</text>
</string>
<string id="st_save_lake_out_bandits">
    <text>vyřízení do tábora stalkerů</text>
</string>
<string id="st_save_lake_na_virychky">
    <text>případ předán Garikovi</text>
</string>
<string id="st_save_lost">
    <text>úkol Ztraceni - splněno</text>
</string>
<string id="st_save_dl_new_time_search_art">
    <text>nový začátek - splněno</text>
</string>


</string_table>
