<?xml version="1.0" encoding="windows-1250"?>
<string_table>
<!-- okr_a5_stalker_texnik Najdi nářadí úrovně 1 -->
<string id="okr_a5_stalker_texnik_task_1_name">
    <text>Najdi nářadí úrovně 1</text>
</string>
<string id="okr_a5_stalker_texnik_task_1_text">
    <text>Stalker technik potřebuje základní nářadí pro vylepšení svého vybavení. Najdi a přines nářadí úrovně 1.</text>
</string>
<string id="okr_a5_stalker_texnik_task_1_about">
    <text>Najdi nářadí úrovně 1 a doruč ho Stalker technikovi, aby mohl vylepšit své vybavení.</text>
</string>
<string id="okr_a5_stalker_texnik_task_1_fetch_about">
    <text>Nářadí úrovně 1</text>
</string>
<string id="okr_a5_stalker_texnik_task_1_fetch_finish">
    <text>Úspěšně jsi doručil nářadí úrovně 1 Stalker technikovi. Nyní je možné provést vylepšení.</text>
</string>

<!-- okr_a5_stalker_texnik Najdi nářadí úrovně 2 -->
<string id="okr_a5_stalker_texnik_task_2_name">
    <text>Najdi nářadí úrovně 2</text>
</string>
<string id="okr_a5_stalker_texnik_task_2_text">
    <text>Stalker technik potřebuje pokročilé nářadí pro další vylepšení. Najdi a přines nářadí úrovně 2.</text>
</string>
<string id="okr_a5_stalker_texnik_task_2_about">
    <text>Najdi nářadí úrovně 2 a doruč ho Stalker technikovi, aby mohl vylepšit své vybavení.</text>
</string>
<string id="okr_a5_stalker_texnik_task_2_fetch_about">
    <text>Nářadí úrovně 2</text>
</string>
<string id="okr_a5_stalker_texnik_task_2_fetch_finish">
    <text>Úspěšně jsi doručil nářadí úrovně 2 Stalker technikovi. Další vylepšení jsou nyní dostupná.</text>
</string>

<!-- okr_a5_stalker_texnik Najdi nářadí úrovně 3 -->
<string id="okr_a5_stalker_texnik_task_3_name">
    <text>Najdi nářadí úrovně 3</text>
</string>
<string id="okr_a5_stalker_texnik_task_3_text">
    <text>Stalker technik potřebuje expertní nářadí pro nejvyšší úroveň vylepšení. Najdi a přines nářadí úrovně 3.</text>
</string>
<string id="okr_a5_stalker_texnik_task_3_about">
    <text>Najdi nářadí úrovně 3 a doruč ho Stalker technikovi, aby dokončil sérii vylepšení.</text>
</string>
<string id="okr_a5_stalker_texnik_task_3_fetch_about">
    <text>Nářadí úrovně 3</text>
</string>
<string id="okr_a5_stalker_texnik_task_3_fetch_finish">
    <text>Úspěšně jsi doručil nářadí úrovně 3 Stalker technikovi. Vylepšení jsou nyní kompletní.</text>
</string>

<!-- a5_stalker_medic_task_1 Najdi lékařskou lékárničku -->
<string id="a5_stalker_medic_task_1_name">
    <text>Najdi lékařskou lékárničku</text>
</string>
<string id="a5_stalker_medic_task_1_text">
    <text>Stalker medik potřebuje lékařskou lékárničku pro své zásoby. Najdi ji a doruč mu ji.</text>
</string>
<string id="a5_stalker_medic_task_1_about">
    <text>Najdi lékařskou lékárničku a přines ji Stalker medikovi, aby mohl léčit zraněné stalkery.</text>
</string>
<string id="a5_stalker_medic_task_1_fetch_about">
    <text>Lékařská lékárnička</text>
</string>
<string id="a5_stalker_medic_task_1_fetch_finish">
    <text>Doručil jsi lékařskou lékárničku Stalker medikovi. Nyní může lépe pečovat o zraněné.</text>
</string>

<!-- b10_docent_1 Najdi nářadí úrovně 1 -->
<string id="b10_docent_1_task_1_name">
    <text>Najdi nářadí úrovně 1</text>
</string>
<string id="b10_docent_1_task_1_text">
    <text>Ekolog docent potřebuje základní nářadí pro své výzkumné účely. Najdi a přines nářadí úrovně 1.</text>
</string>
<string id="b10_docent_1_task_1_about">
    <text>Najdi nářadí úrovně 1 a doruč ho ekologovi docentovi, aby mu pomohlo s výzkumem.</text>
</string>
<string id="b10_docent_1_task_1_fetch_about">
    <text>Nářadí úrovně 1</text>
</string>
<string id="b10_docent_1_task_1_fetch_finish">
    <text>Doručil jsi nářadí úrovně 1 ekologovi docentovi. Tvá pomoc je oceněna.</text>
</string>
<!-- b10_docent_1 Najdi nářadí úrovně 2 -->
<string id="b10_docent_1_task_2_name">
    <text>Najdi nářadí úrovně 2</text>
</string>
<string id="b10_docent_1_task_2_text">
    <text>Ekolog docent potřebuje pokročilé nářadí pro pokračování svého výzkumu. Najdi a přines nářadí úrovně 2.</text>
</string>
<string id="b10_docent_1_task_2_about">
    <text>Najdi a doruč nářadí úrovně 2 ekologovi docentovi pro jeho výzkumné potřeby.</text>
</string>
<string id="b10_docent_1_task_2_fetch_about">
    <text>Nářadí úrovně 2</text>
</string>
<string id="b10_docent_1_task_2_fetch_finish">
    <text>Doručil jsi nářadí úrovně 2 ekologovi docentovi. Výzkum může pokračovat.</text>
</string>

<!-- b10_docent_1 Najdi nářadí úrovně 3 -->
<string id="b10_docent_1_task_3_name">
    <text>Najdi nářadí úrovně 3</text>
</string>
<string id="b10_docent_1_task_3_text">
    <text>Ekolog docent potřebuje expertní nářadí pro dokončení svých experimentů. Najdi a přines nářadí úrovně 3.</text>
</string>
<string id="b10_docent_1_task_3_about">
    <text>Doruč nářadí úrovně 3 ekologovi docentovi, aby dokončil svůj vědecký výzkum.</text>
</string>
<string id="b10_docent_1_task_3_fetch_about">
    <text>Nářadí úrovně 3</text>
</string>
<string id="b10_docent_1_task_3_fetch_finish">
    <text>Doručil jsi nářadí úrovně 3 ekologovi docentovi. Výzkum je nyní dokončen.</text>
</string>

<!-- b10_professor_task_1 Najdi lékařskou lékárničku -->
<string id="b10_professor_task_1_name">
    <text>Najdi lékařskou lékárničku</text>
</string>
<string id="b10_professor_task_1_text">
    <text>Ekolog profesor potřebuje lékařskou lékárničku pro své terénní práce. Najdi ji a doruč mu ji.</text>
</string>
<string id="b10_professor_task_1_about">
    <text>Najdi lékařskou lékárničku a přines ji ekologovi profesorovi, aby mohl bezpečně pokračovat ve své práci.</text>
</string>
<string id="b10_professor_task_1_fetch_about">
    <text>Lékařská lékárnička</text>
</string>
<string id="b10_professor_task_1_fetch_finish">
    <text>Doručil jsi lékařskou lékárničku ekologovi profesorovi. Nyní může bezpečně pokračovat ve své práci.</text>
</string>




</string_table>
